LICENSE.txt
MANIFEST.in
README.rst
requirements.txt
setup.py
Minos.egg-info/PKG-INFO
Minos.egg-info/SOURCES.txt
Minos.egg-info/dependency_links.txt
Minos.egg-info/requires.txt
Minos.egg-info/top_level.txt
minos/__init__.py
minos/errors.py
minos/mixin.py
minos/validator.py
minos/tests/__init__.py
minos/tests/test_mixin.py
minos/tests/test_validator.py
minos/tests/validators/__init__.py
minos/tests/validators/test_datetime_validator.py
minos/tests/validators/test_email_validator.py
minos/tests/validators/test_inclusion_validator.py
minos/tests/validators/test_json_validator.py
minos/tests/validators/test_length_validator.py
minos/tests/validators/test_minimum_presence_validator.py
minos/tests/validators/test_numericality_validator.py
minos/tests/validators/test_presence_validator.py
minos/tests/validators/test_with_validator.py
minos/validators/__init__.py
minos/validators/datetime_validator.py
minos/validators/email_validator.py
minos/validators/inclusion_validator.py
minos/validators/json_validator.py
minos/validators/length_validator.py
minos/validators/minimum_presence_validator.py
minos/validators/numericality_validator.py
minos/validators/phone_validator.py
minos/validators/postal_code_validator.py
minos/validators/presence_validator.py
minos/validators/with_validator.py