Metadata-Version: 1.0
Name: Minos
Version: 0.1.2
Summary: Minos is a library to do flexible validation of Python objects
Home-page: https://github.com/uber/minos
Author: Kevin Novak
Author-email: kevin@uber.com
License: UNKNOWN
Keywords: tests,validation
Platform: UNKNOWN
Classifier: Development Status :: 3 - Alpha
Classifier: Programming Language :: Python
Classifier: Intended Audience :: Developers
Classifier: License :: OSI Approved :: MIT License
Classifier: Operating System :: OS Independent
Classifier: Topic :: Software Development :: Testing
Classifier: Topic :: Software Development :: Libraries :: Python Modules
